gatsby_normalizer
