Metadata-Version: 1.1
Name: gatsby-normalizer
Version: 1.0.3
Summary: Normalize Keyword, URL, and etc.
Home-page: https://github.com/Gatsby-Lee/GatsbyPythonNormalizer
Author: Gatsby Lee
Author-email: gatsbylee.dev@gmail.com
License: UNKNOWN
Keywords: gatsby,normalizer
Platform: UNKNOWN
Classifier: Development Status :: 5 - Production/Stable
Classifier: License :: OSI Approved :: GNU Lesser General Public License v3 (LGPLv3)
Classifier: Intended Audience :: Developers
Classifier: Operating System :: OS Independent
Classifier: Programming Language :: Python
Classifier: Programming Language :: Python :: 3.6
